pyducontrol_csongoose/__init__.py
pyducontrol_csongoose/pyducontrol.py
pyducontrol_csongoose-0.0.2.dist-info/LICENSE.md
pyducontrol_csongoose-0.0.2.dist-info/METADATA
pyducontrol_csongoose-0.0.2.dist-info/WHEEL
pyducontrol_csongoose-0.0.2.dist-info/top_level.txt
pyducontrol_csongoose-0.0.2.dist-info/RECORD
