Metadata-Version: 2.1
Name: pyducontrol-csongoose
Version: 0.0.2
Summary: A small package for communicating with an arduino using commands
Author-email: csongoose <csongoose@gmail.com>
Project-URL: Source code, https://github.com/csongoose/pyducontrol
Classifier: Programming Language :: Python :: 3
Classifier: License :: OSI Approved :: MIT License
Classifier: Operating System :: OS Independent
Requires-Python: >=3.7
License-File: LICENSE.md
Requires-Dist: pyserial
